{"cmd": {"file": "CHI-s55-i35-k10-mean.json", "gold": ["../../gold/all/dole", "../../gold/all/eac_clean.txt", "../../gold/all/justia.txt", "../../gold/all/oxford-dictionary.txt", "../../gold/all/uscourts"], "output": "results/CHI-s55-i35-k10-mean.json", "keep": null, "stem": true, "split": false, "unigrams": true, "verbose": true, "_date": "2022-08-12T15:16:02.247332", "_timestamp": 1660310162.24735, "_cmd": "/home/memonick/EvenTDT/tools/evaluation/terms.py --file CHI-s55-i35-k10-mean.json --gold ../../gold/all/dole ../../gold/all/eac_clean.txt ../../gold/all/justia.txt ../../gold/all/oxford-dictionary.txt ../../gold/all/uscourts --output results/CHI-s55-i35-k10-mean.json --stem --unigram --verbose"}, "pcmd": {"file": "CHI-s55-i35-k10-mean.json", "gold": {"astroturf": "astroturfing", "autocraci": "autocracy", "bicamer": "bicameralism", "brief": "Brief", "bureaucraci": "bureaucracy", "cabinet": "cabinet", "casework": "casework", "caucu": "caucus", "clotur": "cloture", "conserv": "conservation", "constitu": "constituency", "constitution": "constitutionalism", "deleg": "delegate", "democraci": "democracy", "deregul": "deregulation", "deterr": "deterrence", "devolut": "devolution", "feder": "federalism", "filibust": "filibuster", "frame": "framing", "front-runn": "front-runner", "gerrymand": "gerrymandering", "govern": "government", "grants-in-aid": "grants-in-aid", "grassroots-": "grassroots-", "impeach": "Impeachment", "implement": "implementation", "incumb": "incumbent", "initi": "initiative", "institut": "institutions", "jurisdict": "Jurisdiction", "liber": "liberalism", "lobbi": "lobbying", "logrol": "logrolling", "moot": "Moot", "multilater": "multilateralism", "nomin": "nomination", "oligarchi": "oligarchy", "opinion": "Opinion", "patronag": "patronage", "plaintiff": "Plaintiff", "plural": "plurality", "preced": "Precedent", "prime": "priming", "privat": "privatization", "psepholog": "psephology", "pundit": "pundit", "referendum": "referendum", "regul": "regulation", "rule-mak": "rule-making", "sovereignti": "sovereignty", "subsidi": "subsidies", "suffrag": "suffrage", "truste": "Trustee", "tyranni": "tyranny", "uncontrol": "uncontrollables", "unilater": "unilateralism", "absent": "absent", "abstain": "abstain", "access": "accessibility", "accord": "accordance", "accredit": "accreditation", "accuraci": "accuracy", "act": "acting", "administ": "administer", "administr": "administration", "adopt": "adopt", "advoc": "advocate", "affidavit": "Affidavit", "affili": "affiliation", "affirm": "Affirmed", "affix": "affix", "against": "against", "alderman": "alderman", "alderwoman": "alderwoman", "alloc": "allocate", "appeal": "Appeal", "appel": "Appellate", "applic": "application", "appoint": "appointment", "appointe": "appointee", "apportion": "apportionment", "appropri": "appropriation", "approv": "approve", "articl": "article", "assembl": "assembly", "assemblyman": "assemblyman", "assemblyperson": "assemblyperson", "assemblywoman": "assemblywoman", "assessor": "assessor", "assist": "assistance", "attest": "attest", "audit": "audit", "auditor": "auditor", "auditor-control": "auditor-controller", "author": "authority", "avail": "availability", "ballot": "ballot", "biennial": "biennial", "biennium": "biennium", "bill": "bill", "bipartisan": "bipartisan", "bipartisanship": "bipartisanship", "birthdat": "birthdate", "blank": "blank", "blind": "blind", "board": "board", "bond": "bond", "booth": "booth", "borough": "borough", "campaign": "campaign", "cancel": "cancellation", "candidaci": "candidacy", "candid": "candidate", "canvass": "canvassing", "cast": "caste", "categori": "categories", "certif": "Certification", "certifi": "certify", "chad": "chad", "chairman": "chairman", "chairwoman": "chairwoman", "challeng": "challenger", "charter": "charter", "check": "check", "checkmark": "checkmark", "choic": "choice", "choos": "choose", "circul": "circulator", "citizen": "citizen", "citizen-sponsor": "citizen-sponsored", "claim": "Claim", "claimant": "claimant", "clerk": "clerk", "code": "code", "collect": "collect", "collector": "collector", "column": "column", "commiss": "commission", "commission": "commissioner", "committe": "committee", "committeeman": "committeeman", "committeewoman": "committeewoman", "complet": "completeness", "complianc": "compliance", "compon": "component", "comptrol": "comptroller", "compulsori": "compulsory", "confirm": "Confirmation", "conform": "conformance", "congress": "Congress", "congression": "congressional", "congressman": "congressman", "congresswoman": "congresswoman", "constabl": "constable", "constitut": "constitution", "contest": "contest", "contribut": "contribution", "control": "controller", "conven": "convene", "convent": "Convention", "coron": "coroner", "correct": "correct", "council": "council", "councilman": "councilman", "councilperson": "councilperson", "councilwoman": "councilwoman", "count": "Count", "counti": "county", "court": "Court", "court-approv": "court-approved", "courthous": "courthouse", "cross-fil": "cross-filing", "cryptographi": "cryptography", "current": "current", "deadlin": "deadline", "decertif": "decertification", "decrypt": "decryption", "defeat": "defeat", "delet": "delete", "democrat": "democratization", "deputi": "deputy", "design": "designation", "detach": "detach", "devic": "device", "director": "director", "disabl": "disabled", "disclosur": "disclosure", "discrimin": "discrimination", "display": "display", "disqualif": "disqualification", "disqualifi": "disqualifying", "district": "district", "divis": "division", "double-check": "double-check", "due": "due", "e-vot": "e-voting", "elect": "election", "election": "electioneer", "elector": "electorate", "elig": "eligible", "enact": "enactment", "enclos": "enclose", "encrypt": "encryption", "enrol": "enrollment", "entri": "entry", "envelop": "envelope", "equip": "equipment", "erasur": "erasure", "ethic": "ethics", "exempt": "exempt", "expenditur": "expenditures", "expens": "expense", "expir": "expired", "extens": "extension", "federalist": "Federalist", "feloni": "Felony", "file": "File", "fill": "fill", "fine": "fine", "firmwar": "firmware", "fiscal": "fiscal", "flap": "flap", "fold": "fold", "form": "form", "fraud": "Fraud", "fraudul": "fraudulent", "full-screen": "full-screen", "function": "functionalism", "fund": "fund", "fundrais": "fundraising", "gener": "general", "governor": "governor", "gubernatori": "gubernatorial", "guidelin": "guidelines", "handicap": "handicapped", "hash": "hash", "hear": "hearing", "herebi": "hereby", "heretofor": "heretofore", "herewith": "herewith", "identif": "identification", "inact": "inactive", "independ": "Independent", "inelig": "ineligible", "ink": "ink", "insert": "insert", "inspect": "inspection", "inspector": "inspector", "instruct": "Instructions", "integr": "integrity", "intent": "intent", "interpret": "interpreter", "irregular": "irregularities", "issu": "Issue", "judg": "Judge", "judici": "judicial", "juri": "Jury", "justic": "justice", "languag": "language", "law": "law", "legal": "legally", "legisl": "legislator", "legislatur": "legislature", "libertarian": "libertarianism", "lieuten": "lieutenant", "lobbyist": "lobbyists", "local": "local", "machin": "machine", "magistr": "magistrate", "mail": "mail", "major": "majority", "malfunct": "malfunctions", "mandat": "mandate", "mandatori": "mandatory", "mark": "mark", "marksens": "Marksense", "mayor": "mayor", "measur": "measure", "member": "member", "membership": "membership", "mismark": "mismarked", "moder": "moderate", "municip": "municipality", "nation": "nationalization", "nomine": "nominee", "non-author": "non-authorized", "non-partisan": "non-partisan", "noncompli": "noncompliance", "nondiscriminatori": "nondiscriminatory", "notic": "notice", "notif": "notification", "notifi": "notify", "notwithstand": "notwithstanding", "oath": "oath", "observ": "observers", "offic": "offices", "offici": "official", "open": "open", "oppon": "opponent", "oppos": "oppose", "option": "optional", "order": "order", "ordin": "ordinance", "out-of-st": "out-of-state", "overvot": "overvoting", "parish": "parish", "partisan": "partisan", "parti": "party", "penalti": "Penalty", "perman": "permanent", "petit": "Petition", "platform": "platform", "plebiscit": "plebiscite", "pointer": "pointer", "polici": "policy", "polit": "politics", "politician": "politician", "poll": "poll", "popul": "populism", "posit": "position", "post-elect": "post-election", "postag": "postage", "postmark": "postmark", "pre-clear": "pre-clearance", "precandidaci": "precandidacy", "precinct": "precinct", "precis": "precision", "presid": "president", "presidenti": "presidential", "primari": "primary", "privaci": "privacy", "procedur": "Procedure", "process": "process", "proclam": "proclamation", "propon": "proponent", "propos": "proposed", "proposit": "proposition", "prothonotari": "prothonotary", "provis": "provision", "puncher": "puncher", "purg": "purge", "qualif": "qualification", "qualifi": "qualify", "ratif": "ratification", "ratifi": "ratify", "re-elect": "re-election", "reappoint": "reappointment", "reapport": "reapportion", "reapportion": "reapportionment", "recal": "recall", "receipt": "receipt", "recertif": "recertification", "reconcil": "reconcile", "record": "Record", "recount": "recount", "redistrict": "redistricting", "referenda": "referenda", "reform": "reform", "regist": "registered", "registr": "registration", "registrar": "registrar", "registration-by-mail": "registration-by-mail", "reinstat": "reinstatement", "reject": "reject", "remov": "remove", "repeal": "repeal", "repres": "representative", "reproduc": "reproducibility", "republican": "republicanism", "request": "requested", "requir": "requirement", "reregist": "reregister", "resolut": "resolution", "restrict": "restrictions", "result": "results", "retain": "retain", "return": "Return", "revis": "revision", "rezon": "rezoning", "right": "rights", "roster": "roster", "rule": "rule", "run-off": "run-off", "scan-lin": "scan-line", "scanner": "scanner", "scan": "scanning", "scroll": "scroll", "seal": "seal", "seat": "seat", "secretari": "secretary", "select": "selection", "senat": "senate", "senatori": "senatorial", "senior": "seniority", "sheriff": "sheriff", "sign": "sign", "signatur": "signature", "site": "sites", "slate": "slate", "sleev": "sleeve", "slide": "slide", "slip": "slip", "softwar": "software", "spoil": "spoil", "state": "state", "statement": "statement", "statewid": "statewide", "statut": "Statute", "stub": "stub", "stylu": "stylus", "subdivis": "subdivision", "submit": "submit", "successor": "successor", "superintend": "superintendent", "supervisor": "supervisor", "swear": "swear", "sworn": "sworn", "t-coil": "t-coil", "tabul": "tabulator", "talli": "tally", "tape": "tape", "tax": "tax", "tear": "tear", "telecommun": "telecommunications", "term": "term", "test": "test", "ticket": "ticket", "torn": "torn", "town": "town", "township": "township", "translat": "translator", "treasur": "treasurer", "treasuri": "treasury", "tribun": "tribunal", "turnout": "turnout", "unconstitut": "unconstitutional", "undervot": "undervoting", "unenrol": "unenrolled", "unexpir": "unexpired", "unif": "unification", "usabl": "usability", "vacanc": "vacancy", "valid": "validation", "verif": "verification", "verifi": "verify", "veto": "veto", "vice-": "vice-", "vice-presidenti": "vice-presidential", "violat": "Violation", "void": "voided", "vote": "voting", "voter": "voter", "voter-verifi": "voter-verifiable", "votomat": "Votomatic", "waiv": "waive", "waiver": "waiver", "ward": "ward", "whip": "whip", "withdraw": "withdrawal", "wit": "Witness", "write-in": "write-in", "zone": "zoning", "accessori": "Accessory", "accomplic": "Accomplice", "acquitt": "Acquittal", "adult": "Adult", "alibi": "Alibi", "arraign": "Arraignment", "arson": "Arson", "bail": "Bail", "batteri": "Battery", "book": "Booking", "burglari": "Burglary", "citat": "Citation", "cite": "Cited", "commit": "Commit", "commut": "Commutation", "convers": "Conversion", "convict": "Conviction", "crime": "Crime", "custodi": "Custody", "deced": "Decedent", "defend": "Defendant", "divers": "Diversion", "drunken": "Drunkenness", "embezzl": "Embezzlement", "entrap": "Entrapment", "expung": "Expungement", "extradit": "extradition", "gambl": "Gambling", "immun": "Immunity", "incarcer": "Incarceration", "incrimin": "Incriminate", "indict": "Indictment", "indig": "Indigent", "inform": "Information", "infract": "Infraction", "innoc": "Innocent", "jeopardi": "Jeopardy", "juvenil": "Juvenile", "larceni": "Larceny", "larceny-theft": "Larceny-Theft", "lenienc": "Leniency", "maim": "Maim", "mayhem": "Mayhem", "misdemeanor": "Misdemeanor", "mitig": "Mitigation", "modif": "Modification", "murder": "Murder", "nonservic": "Nonservice", "offens": "Offense", "pardon": "Pardon", "parol": "Parole", "perjuri": "Perjury", "plea": "Plea", "present": "Presentment", "probat": "Probation", "prosecut": "Prosecute", "prosecutor": "Prosecutor", "rape": "Rape", "recidivist": "Recidivist", "referr": "Referral", "remand": "Remand", "revoc": "Revocation", "robberi": "Robbery", "self-defens": "Self-Defense", "self-surrend": "Self-Surrender", "sentenc": "Sentence", "suppress": "Suppress", "suspicion": "Suspicion", "unfound": "Unfounded", "vagranc": "Vagrancy", "vandal": "Vandalism", "warrant": "Warrant", "weapon": "Weapons", "abort": "abortion", "absolut": "absolutism", "account": "accountability", "activist": "activist", "adjournment((debate))": "adjournment((debate))", "age": "age", "agenc": "agency", "aggreg": "aggregation", "aid": "aid", "al\u2010qaeda": "al\u2010Qaeda", "alien": "alienation", "allianc": "alliances", "altruism": "altruism", "amend": "amendment", "amen": "amenity", "america": "America", "am": "AMS", "anarch": "anarchism", "anarcho\u2010synd": "anarcho\u2010syndicalism", "anarchi": "anarchy", "anc": "ANC", "anomi": "anomie", "anthropocentr": "anthropocentrism", "anthropolog": "anthropology", "anti\u2010glob": "anti\u2010globalization", "anti\u2010semit": "anti\u2010Semitism", "anticler": "anticlericalism", "anzu": "ANZUS", "apartheid": "apartheid", "apparat": "apparat", "apparent": "apparentement", "appeas": "appeasement", "aristocraci": "aristocracy", "articul": "articulation", "asean": "ASEAN", "asylum": "asylum", "auster": "austerity", "autarchi": "autarchy", "authoritarian": "authoritarianism", "autogest": "autogestion", "autonomi": "autonomy", "av": "AV", "avicenna": "Avicenna", "ayatollah": "Ayatollah", "ba\u2019ath": "Ba\u2019athism", "back-bench": "back-bencher", "backlash": "backlash", "balkan": "Balkanization", "bandwagon": "bandwagoning", "base": "base", "behaviour(al)": "behaviour(al)ism", "beltway": "beltway", "benelux": "Benelux", "beveridge((report))": "Beveridge((Report))", "bilater": "bilateralism", "bioethic": "bioethics", "bipolar": "bipolarity", "bolshev": "Bolshevism", "bonapart": "Bonapartism", "bourgeoisi": "bourgeoisie", "boycott": "boycott", "brexit": "Brexit", "bric": "BRIC", "brinkmanship": "brinkmanship", "buck-pass": "buck-passing", "budget": "budgeting", "butskel": "Butskellism", "butterfly-ballot": "butterfly-ballot", "cadr": "cadre", "cap": "CAP", "capit": "capitalism", "carpet\u2010bagg": "carpet\u2010bagger", "castroism": "Castroism", "caudillismo": "caudillismo", "charisma": "charisma", "chariti": "charity", "chicken": "Chicken", "cia": "CIA", "citizenship": "citizenship", "class": "class", "cleavag": "cleavage", "clerisi": "clerisy", "clientel": "clientelism", "closur": "closure", "cnd": "CND", "co\u2010decis": "co\u2010decision", "coalit": "coalition", "cohabit": "cohabitation", "collectiv": "collectivization", "coloni": "colonialism", "comitolog": "comitology", "commodity\u2010fetish": "commodity\u2010fetishism", "commonwealth((british))": "Commonwealth((British))", "commun": "community", "communitarian": "communitarianism", "condition": "conditionality", "confeder": "confederation", "confuciu": "Confucius", "congress((india))": "Congress((India))", "congress((usa))": "Congress((USA))", "consensu": "consensus", "consent": "consent", "consequenti": "consequentialism", "conservat": "conservatism", "constructiv": "constructivism", "contain": "containment", "context": "context", "contract": "Contract", "contradict": "contradiction", "corpor": "corporation", "corporat": "corporatism", "corrupt": "corruption", "cosmopolitan": "cosmopolitanism", "counter\u2010insurg": "counter\u2010insurgency", "coven": "covenant", "cronyism": "cronyism", "cross\u2010bench": "cross\u2010bench", "csce": "CSCE", "cusanu": "Cusanus", "cyber-attack": "cyber-attack", "cyber-crim": "cyber-crime", "cyber-secur": "cyber-security", "cyber-terror": "cyber-terrorism", "cycl": "cycle", "d\u2019holbach": "d\u2019Holbach", "da\u2019esh": "Da\u2019esh", "darfur": "Darfur", "darwin": "Darwinism", "dealign": "dealignment", "decolon": "decolonization", "deflat": "deflation", "delimit": "delimitation", "demagogu": "demagogue", "demarchi": "demarchy", "deontolog": "deontology", "depend": "dependency", "desegreg": "desegregation", "despot": "despotism", "detent": "d\u00e9tente", "develop": "development", "dictatorship": "dictatorship", "digger": "Diggers", "dignifi": "dignified", "diplomaci": "diplomacy", "directive((eu))": "directive((EU))", "dirigism": "dirigisme", "disarma": "disarmament", "dissolut": "dissolution", "dominion": "dominion", "dyad": "dyad", "dyarchi": "dyarchy", "east": "East", "ecocentr": "ecocentrism", "ecolog": "ecology", "egalitarian": "egalitarianism", "elit": "elitism", "emancip": "emancipation", "emigr": "emigration", "empir": "empire", "em": "EMS", "emu": "EMU", "endogen": "endogeneity", "entitl": "entitlement", "entrench": "entrenchment", "entryism": "entryism", "environment": "environmentalism", "epa": "EPA", "epistemolog": "epistemology", "equal": "equality", "equilibrium": "equilibrium", "equiti": "Equity", "ethnic": "ethnicity", "ethnocentr": "ethnocentrism", "euro": "euro", "eurocentr": "Eurocentrism", "eurocommun": "Eurocommunism", "europ": "Europe", "euroscept": "eurosceptic", "euthanasia": "euthanasia", "evolut": "evolution", "execut": "executive", "existenti": "existentialism", "][": "][", "exit": "exit", "exogen": "exogeneity", "exploit": "exploitation", "extern": "externalities", "fabian": "Fabianism", "faction": "faction", "falsifi": "falsifiability", "fascism": "fascism", "fatah": "Fatah", "fatwa": "fatwa", "fbi": "FBI", "fear": "fear", "femin": "feminism", "feudal": "feudalism", "first-past-the-post": "first-past-the-post", "fordism": "fordism", "franchis": "franchise", "franco(ism)": "Franco(ism)", "fratern": "fraternity", "freedom": "freedom", "front-bench": "front-bencher", "g20": "G20", "g7": "G7", "g77": "G77", "gat": "GATS", "gatt": "GATT", "gaullism": "Gaullism", "gcc": "GCC", "gdp": "GDP", "gemeinschaft": "Gemeinschaft", "genocid": "genocide", "geopolit": "geopolitics", "gesellschaft": "Gesellschaft", "girondin": "Girondins", "glasnost": "glasnost", "global": "globalization", "gnp": "GNP", "gop": "GOP", "government": "governmentality", "gracchu": "Gracchus", "greenpeac": "Greenpeace", "groupthink": "groupthink", "guillotin": "guillotine", "gulag": "Gulag", "hansard": "Hansard", "hawk": "hawk", "hegemoni": "hegemony", "heresthetic(s)": "heresthetic(s)", "hermeneut": "hermeneutics", "hindutva": "Hindutva", "historic": "historicism", "homogen": "homogenization", "housework": "housework", "hyperglob": "hyperglobalism", "iaea": "IAEA", "ideal": "idealism", "ideolog": "ideology", "imf": "IMF", "immigr": "immigration", "immobilism": "immobilisme", "imperi": "imperialism", "impound": "impoundment", "increment": "incrementalism", "individu": "individualism", "inflat": "inflation", "ingo": "INGO", "insurg": "insurgency", "intellig": "intelligence", "intelligentsia": "intelligentsia", "interdepend": "interdependence", "intergovernment": "intergovernmentalism", "intermest": "intermestic", "internation": "internationalism", "intern": "internment", "intifada": "intifada", "irredent": "irredentism", "isi": "ISIS", "isolation": "isolationism", "j-curv": "J-curve", "jacobin": "Jacobinism", "jacobit": "Jacobitism", "janjawe": "janjaweed", "jerrymand": "jerrymandering", "jihad": "jihad", "jingoism": "jingoism", "judaism": "Judaism", "judiciari": "judiciary", "junta": "junta", "jurisprud": "Jurisprudence", "jury((theorem))": "jury((theorem))", "kashmir": "Kashmir", "kemal": "Kemalism", "kibbutz": "kibbutz", "kinship": "kinship", "kulak": "kulak", "laissez-fair": "laissez-faire", "lamarck": "Lamarckism", "left": "left", "legitimaci": "legitimacy", "lenin": "Leninism", "level": "Levellers", "liberti": "liberty", "linkag": "linkage", "loyalti": "loyalty", "lumpenproletariat": "lumpenproletariat", "macroeconom": "macroeconomics", "mafia": "Mafia", "majoritarian": "majoritarianism", "maladministr": "maladministration", "manifesto": "manifesto", "manipul": "manipulation", "margin": "marginalism", "market": "market", "marxism": "Marxism", "mass": "masses", "materi": "materialism", "matriarchi": "matriarchy", "maximin": "maximin", "mccarthyism": "McCarthyism", "mcdonald": "McDonaldization", "mdg": "MDGs", "menshevik": "Mensheviks", "mercantil": "mercantilism", "mercosur": "MERCOSUR", "meritocraci": "meritocracy", "meta-theori": "meta-theory", "methodolog": "methodology", "mfn": "MFN", "mi5": "MI5", "mi6": "MI6", "microeconom": "microeconomics", "migrat": "migration", "militar": "militarism", "millenarian": "millenarianism", "minimax": "minimax", "minist": "Minister", "mobil": "mobility", "modern": "modernization", "monad": "monadic", "monarch": "monarchism", "monetar": "monetarism", "monoton": "monotonicity", "multicultur": "multiculturalism", "multipolar": "multipolarity", "nafta": "NAFTA", "narodnik": "Narodnik", "nation-st": "nation-state", "nato": "NATO", "nazi": "Nazi", "need": "needs", "neo-coloni": "neo-colonialism", "neo-fasc": "neo-fascism", "neo-marx": "neo-Marxism", "neoconservat": "neoconservatism", "neocorporat": "neocorporatism", "neofunction": "neofunctionalism", "neoliber": "neoliberalism", "neoreal": "neorealism", "nep": "NEP", "network": "networks", "neutral": "neutrality", "ngo": "NGO", "nimbyism": "nimbyism", "nomenklatura": "nomenklatura", "non-align": "non-alignment", "non-refoul": "non-refoulement", "non\u2010viol": "non\u2010violence", "norm": "norm", "north": "North", "oa": "OAS", "oau": "OAU", "obedi": "obedience", "oblig": "obligation", "oecd": "OECD", "oligarch": "oligarch", "oligopoli": "oligopoly", "ombudsman": "ombudsman", "ontolog": "ontology", "opec": "OPEC", "orient": "orientalism", "ostpolitik": "Ostpolitik", "pac((uk))": "PAC((UK))", "pac((usa))": "PAC((USA))", "pacif": "pacifism", "pair": "pairing", "pan-african": "Pan-Africanism", "pan-arab": "Pan-Arabism", "panachag": "panachage", "pancasila": "pancasila", "panscheel": "panscheel", "pantouflag": "pantouflage", "pardon((presidential))": "pardon((Presidential))", "parliament": "parliament", "partit": "partition", "patern": "paternalism", "patriarchi": "patriarchy", "patriot": "patriotism", "peacebuild": "peacebuilding", "peacekeep": "peacekeeping", "peasantri": "peasantry", "pentagon": "Pentagon", "perestroika": "perestroika", "perfection": "perfectionism", "pericl": "Pericles", "peron(ism)": "Per\u00f3n(ism)", "pfi": "PFI", "phenomenolog": "phenomenology", "physiocrat": "physiocrats", "pillar": "pillarization", "plan": "Plan", "plo": "PLO", "polar": "polarization", "polic": "police", "poli": "polis", "politburo": "Politburo", "polyarchi": "polyarchy", "pornographi": "pornography", "positiv": "positivism", "post-coloni": "post-colonialism", "post-ford": "post-fordism", "post-industri": "post-industrialism", "post-materi": "post-materialism", "post-modern": "post-modernism", "post-positiv": "post-positivism", "post-structur": "post-structuralism", "poujad": "Poujadism", "poverti": "poverty", "power": "power", "power-shar": "power-sharing", "ppp": "PPP", "prefect": "prefect", "prefer": "preference", "prerog": "prerogative", "president-elect": "president-elect", "pro-choic": "pro-choice", "pro-lif": "pro-life", "proletariat": "proletariat", "propaganda": "propaganda", "properti": "property", "protection(ism)": "protection(ism)", "protector": "Protectorate", "psbr": "PSBR", "psycholog": "psychology", "publiu": "Publius", "punish": "punishment", "quaker": "Quakers", "quango": "quango", "quorum": "quorum", "radical-right": "radical-right", "reactionari": "reactionary", "realign": "realignment", "realism((classical))": "realism((classical))", "realism": "realism", "realpolitik": "realpolitik", "reflectiv": "reflectivism", "refuge": "refugee", "regim": "regime", "region": "regionalization", "reific": "reification", "relativ": "relativism", "rendit": "rendition", "rent-seek": "rent-seeking", "repar": "reparations", "represent": "representation", "republ": "republic", "reselect": "reselection", "reserv": "reservation", "resili": "resilience", "revision": "revisionism", "revolut": "revolution", "rhetor": "rhetoric", "rider": "rider", "right(-wing)": "right(-wing)", "risk": "risk", "risorgimento": "Risorgimento", "roll-cal": "roll-call", "romantic": "Romanticism", "rwanda": "Rwanda", "saddlepoint": "saddlepoint", "salienc": "salience", "salt": "SALT", "sampl": "sampling", "sanction": "Sanction", "sandin": "Sandinism", "sans-culott": "sans-culottes", "sdg": "SDGs", "sdi": "SDI", "sdp": "SDP", "sea": "SEA", "seato": "SEATO", "secess": "secession", "secular": "secularization", "securit": "securitization", "segreg": "segregation", "self-determin": "self-determination", "self-govern": "self-government", "self-interest": "self-interest", "self-ownership": "self-ownership", "sexism": "sexism", "shari\u2019a": "shari\u2019a", "shi\u2019i": "Shi\u2019i", "side-constraint": "side-constraint", "single-peaked": "single-peakedness", "sittlichkeit": "sittlichkeit", "slaveri": "slavery", "social": "socialism", "societi": "society", "sociobiolog": "sociobiology", "sociolog": "sociology", "solidar": "Solidarity", "sophist": "sophists", "sortit": "sortition", "south": "South", "sparta": "Sparta", "spartacist": "Spartacists", "spd((germany))": "SPD((Germany))", "speaker": "Speaker", "species-b": "species-being", "spin": "spin", "spitzenkandidaten": "spitzenkandidaten", "sport": "sport", "stakehold": "stakeholder", "stakhanov": "Stakhanovism", "stalin": "Stalinism", "start": "START", "statecraft": "statecraft", "statism": "statism", "stoicism": "Stoicism", "stop-go": "stop-go", "strategi": "strategy", "strategy-proof": "strategy-proofness", "structur": "structure", "subsidiar": "subsidiarity", "subvers": "subversion", "suffragett": "suffragette", "suffragist": "suffragist", "sunni": "Sunni", "supergam": "supergame", "superpow": "superpower", "superstructur": "superstructure", "supranation": "supranationalism", "supraterritori": "supraterritoriality", "swing": "swing", "syndic": "syndicalism", "taliban": "Taliban", "taylor": "Taylorism", "terror": "terrorism", "thatcher": "Thatcherism", "theocraci": "theocracy", "think-tank": "think-tanks", "thomism": "Thomism", "ticket-split": "ticket-splitting", "titoism": "Titoism", "toler": "toleration", "tortur": "torture", "toryism": "Toryism", "totalitarian": "totalitarianism", "tradition": "traditionalism", "transit": "transitivity", "transnation": "transnationalism", "trotskyism": "Trotskyism", "trusteeship": "trusteeship", "udi": "UDI", "ulster": "Ulster", "un": "UN", "unanim": "unanimity", "uncertainti": "uncertainty", "unctad": "UNCTAD", "underclass": "underclass", "unga": "UNGA", "ungovern": "ungovernability", "unicamer": "unicameralism", "unilateralism((uk))": "unilateralism((UK))", "union": "unionism", "unipolar": "unipolarity", "unmov": "UNMOVIC", "unsc": "UNSC", "urban": "urbanism", "utilitarian": "utilitarianism", "util": "utility", "utopian": "utopianism", "ver": "VER", "vice-presid": "Vice-President", "vichi": "Vichy", "violenc": "violence", "voic": "voice", "want": "wants", "war": "war", "warlord": "warlordism", "waterg": "Watergate", "wellb": "wellbeing", "west": "West", "westminst": "Westminster", "weu": "WEU", "whig": "Whig", "wmd": "WMD", "woolsack": "Woolsack", "xenophobia": "xenophobia", "zapatismo": "zapatismo", "zionism": "Zionism", "zip": "zipping", "admiss": "Admissible", "answer": "Answer", "appelle": "Appellee", "asset": "Assets", "assum": "Assume", "bankruptci": "Bankruptcy", "caseload": "Caseload", "chamber": "Chambers", "chapter": "Chapter 9", "collater": "Collateral", "complaint": "Complaint", "counsel": "Counsel", "creditor": "Creditor", "damag": "Damages", "debtor": "Debtor", "deposit": "Deposition", "discharg": "Discharge", "discoveri": "Discovery", "docket": "Docket", "equit": "Equitable", "evid": "Evidence", "hearsay": "Hearsay", "injunct": "Injunction", "interrogatori": "Interrogatories", "judgeship": "Judgeship", "judgment": "Judgment", "lawsuit": "Lawsuit", "lien": "Lien", "liquid": "Liquidation", "litig": "Litigation", "mistrial": "Mistrial", "motion": "Motion", "panel": "Panel", "plead": "Pleadings", "prioriti": "Priority", "redempt": "Redemption", "revers": "Reverse", "schedul": "Schedules", "sequest": "Sequester", "settlement": "Settlement", "subordin": "Subordination", "subpoena": "Subpoena", "testimoni": "Testimony", "toll": "Toll", "tort": "Tort", "transcript": "Transcript", "transfer": "Transfer", "uphold": "Uphold", "venu": "Venue", "verdict": "Verdict", "writ": "Writ"}, "output": "results/CHI-s55-i35-k10-mean.json", "keep": 400, "stem": true, "split": false, "unigrams": true, "verbose": true, "_date": "2022-08-12T15:16:02.247373", "_timestamp": 1660310162.2473774, "_cmd": "/home/memonick/EvenTDT/tools/evaluation/terms.py --file CHI-s55-i35-k10-mean.json --gold ../../gold/all/dole ../../gold/all/eac_clean.txt ../../gold/all/justia.txt ../../gold/all/oxford-dictionary.txt ../../gold/all/uscourts --output results/CHI-s55-i35-k10-mean.json --stem --unigram --verbose", "terms": ["elect", "vote", "presid", "pardon", "administr", "campaign", "inaugur", "win", "support", "elector", "result", "state", "presidenti", "ralli", "overturn", "voter", "vaccin", "victori", "conced", "fraud", "offic", "plan", "call", "recount", "offici", "team", "transit", "claim", "secretari", "former", "court", "lawsuit", "lost", "poll", "impeach", "trump", "nation", "count", "lead", "certifi", "lie", "legal", "bill", "polici", "democraci", "secur", "last", "feder", "year", "defens", "polit", "speech", "said", "law", "ballot", "veto", "overrid", "file", "colleg", "relief", "foreign", "cast", "widespread", "dose", "judg", "sign", "evid", "packag", "refus", "mail", "dismiss", "challeng", "reject", "receiv", "pass", "stimulu", "appeal", "president-elect", "alleg", "effort", "pick", "execut", "deliv", "check", "counti", "order", "first", "leav", "certif", "nomin", "attempt", "week", "advis", "popular", "govern", "coup", "bid", "block", "fund", "day", "remov", "lawyer", "race", "winner", "introduc", "demand", "econom", "retir", "agenc", "final", "threaten", "senior", "confirm", "next", "vice", "debat", "nomine", "increas", "cabinet", "object", "revers", "invok", "million", "health", "immigr", "announc", "democrat", "investig", "outcom", "chief", "rig", "process", "climat", "suit", "brief", "staff", "intellig", "counsel", "tax", "appoint", "member", "attorney", "new", "remark", "affirm", "gener", "son", "cut", "take", "acknowledg", "educ", "director", "woman", "project", "militari", "troop", "oath", "commun", "republican", "second", "earli", "articl", "time", "power", "clemenc", "term", "senat", "peac", "turnout", "pressur", "posit", "crimin", "press", "death", "cooper", "confer", "runoff", "incit", "crime", "american", "pay", "famili", "address", "fire", "alli", "violenc", "separ", "peopl", "riot", "rais", "hold", "mob", "border", "charg", "resign", "children", "pro-trump", "polic", "account", "money", "attack", "die", "protest", "tri", "say", "suspend", "rioter", "steal", "arrest", "twitter", "capitol", "stop", "assault", "get", "find", "ban", "congratul", "proof", "appointe", "justic", "domest", "governor", "enemi", "servic", "cheat", "terrorist", "destroy", "travel", "leader", "compani", "machin", "ask", "end", "mani", "spent", "chines", "mask", "media", "major", "believ", "russian", "need", "hour", "lose", "work", "wear", "disinform", "countri", "viru", "parti", "want", "group", "send", "think", "uniti", "know", "messag", "go", "make", "tweet", "corrupt", "name", "let", "white", "illeg", "'re", "thing", "way", "black", "person", "email", "man", "lock", "paid", "fight", "done", "right", "clear", "deni", "act", "base", "diplomat", "live", "golf", "see", "cours", "veteran", "save", "play", "choos", "'ve", "hear", "pledg", "today", "break", "dog", "seen", "stand", "news", "got", "step", "job", "record", "coverag", "credit", "doctor", "good", "report", "releas", "close", "crowd", "love", "pre", "led", "video", "statement", "post", "come", "flag", "depart", "watch", "letter", "histor", "flip", "tie", "blue", "full", "look", "defend", "talk", "bad", "open", "landslid", "agreement", "thread", "read", "faith", "kid", "secret", "favor", "remain", "truth", "disput", "privat", "answer", "stori", "run", "admit", "great", "stock", "stage", "document", "big", "minut", "matter", "market", "interview", "reveal", "better", "import", "loser", "financi", "uselect", "oper", "confid", "bet", "speak", "wrote", "fuck", "trust", "walk", "wife", "biggest", "hous", "hell", "mark", "arriv", "photo", "legaci", "biden", "moder", "true", "least", "embarrass", "traitor", "word", "entir", "shut", "thank", "cancel", "hurt", "pleas", "grift", "note", "happi", "crazi", "gone", "endors", "sound", "surpris"]}, "results": {"summary": {"average precision": 0.05021833122833605, "precision": 0.2725, "recall": 0.09308283518360376, "f1": 0.1387651177593889}, "p@k": {"1": 1, "2": 1.0, "3": 1.0, "4": 1.0, "5": 1.0, "6": 1.0, "7": 0.8571428571428571, "8": 0.75, "9": 0.6666666666666666, "10": 0.7, "11": 0.7272727272727273, "12": 0.75, "13": 0.7692307692307693, "14": 0.7142857142857143, "15": 0.6666666666666666, "16": 0.6875, "17": 0.6470588235294118, "18": 0.6111111111111112, "19": 0.5789473684210527, "20": 0.6, "21": 0.6190476190476191, "22": 0.6363636363636364, "23": 0.6086956521739131, "24": 0.625, "25": 0.64, "26": 0.6153846153846154, "27": 0.6296296296296297, "28": 0.6428571428571429, "29": 0.6551724137931034, "30": 0.6333333333333333, "31": 0.6451612903225806, "32": 0.65625, "33": 0.6363636363636364, "34": 0.6470588235294118, "35": 0.6571428571428571, "36": 0.6388888888888888, "37": 0.6486486486486487, "38": 0.6578947368421053, "39": 0.6410256410256411, "40": 0.6500000000000001, "41": 0.6341463414634148, "42": 0.6428571428571429, "43": 0.6511627906976745, "44": 0.6590909090909092, "45": 0.6666666666666667, "46": 0.6521739130434784, "47": 0.6382978723404257, "48": 0.6458333333333335, "49": 0.6326530612244899, "50": 0.6200000000000001, "51": 0.627450980392157, "52": 0.6153846153846155, "53": 0.6037735849056605, "54": 0.6111111111111113, "55": 0.6181818181818183, "56": 0.6250000000000001, "57": 0.6140350877192984, "58": 0.6206896551724139, "59": 0.6101694915254239, "60": 0.6000000000000001, "61": 0.5901639344262296, "62": 0.5967741935483872, "63": 0.5873015873015874, "64": 0.5781250000000001, "65": 0.5846153846153848, "66": 0.590909090909091, "67": 0.5970149253731344, "68": 0.5882352941176472, "69": 0.5797101449275364, "70": 0.5857142857142859, "71": 0.5774647887323945, "72": 0.5833333333333335, "73": 0.5890410958904112, "74": 0.5810810810810814, "75": 0.5733333333333336, "76": 0.5657894736842108, "77": 0.5714285714285717, "78": 0.5769230769230772, "79": 0.5696202531645572, "80": 0.5625000000000002, "81": 0.5555555555555557, "82": 0.5609756097560977, "83": 0.5542168674698796, "84": 0.5595238095238096, "85": 0.5647058823529413, "86": 0.5697674418604652, "87": 0.5632183908045979, "88": 0.556818181818182, "89": 0.5617977528089889, "90": 0.5666666666666669, "91": 0.5604395604395607, "92": 0.5543478260869568, "93": 0.5483870967741937, "94": 0.5425531914893619, "95": 0.5473684210526317, "96": 0.5416666666666669, "97": 0.5360824742268042, "98": 0.5306122448979592, "99": 0.5353535353535354, "100": 0.53, "101": 0.5346534653465347, "102": 0.5294117647058824, "103": 0.5242718446601942, "104": 0.5192307692307693, "105": 0.5142857142857143, "106": 0.509433962264151, "107": 0.5046728971962618, "108": 0.5000000000000002, "109": 0.504587155963303, "110": 0.5000000000000002, "111": 0.4954954954954957, "112": 0.5000000000000002, "113": 0.5044247787610622, "114": 0.5000000000000002, "115": 0.4956521739130437, "116": 0.49137931034482785, "117": 0.49572649572649596, "118": 0.4915254237288138, "119": 0.49579831932773133, "120": 0.4916666666666669, "121": 0.49586776859504156, "122": 0.4918032786885248, "123": 0.4878048780487807, "124": 0.4838709677419357, "125": 0.4880000000000002, "126": 0.48412698412698435, "127": 0.488188976377953, "128": 0.4843750000000002, "129": 0.48062015503875993, "130": 0.4769230769230771, "131": 0.47328244274809184, "132": 0.4772727272727275, "133": 0.473684210526316, "134": 0.4701492537313435, "135": 0.47407407407407426, "136": 0.47058823529411786, "137": 0.47445255474452575, "138": 0.4782608695652176, "139": 0.48201438848920886, "140": 0.48571428571428593, "141": 0.4893617021276598, "142": 0.48591549295774666, "143": 0.4825174825174827, "144": 0.47916666666666685, "145": 0.48275862068965536, "146": 0.48630136986301387, "147": 0.48299319727891177, "148": 0.47972972972972994, "149": 0.47651006711409416, "150": 0.47333333333333355, "151": 0.4701986754966889, "152": 0.473684210526316, "153": 0.4705882352941178, "154": 0.46753246753246774, "155": 0.46451612903225825, "156": 0.46153846153846173, "157": 0.4649681528662422, "158": 0.468354430379747, "159": 0.47169811320754734, "160": 0.46875000000000017, "161": 0.46583850931677034, "162": 0.469135802469136, "163": 0.46625766871165664, "164": 0.4695121951219514, "165": 0.46666666666666684, "166": 0.46987951807228934, "167": 0.47305389221556904, "168": 0.4702380952380954, "169": 0.4733727810650889, "170": 0.4705882352941178, "171": 0.47368421052631593, "172": 0.4709302325581397, "173": 0.4682080924855493, "174": 0.4655172413793105, "175": 0.462857142857143, "176": 0.4602272727272729, "177": 0.45762711864406797, "178": 0.45505617977528107, "179": 0.45810055865921806, "180": 0.4555555555555557, "181": 0.45303867403314935, "182": 0.4505494505494507, "183": 0.44808743169398924, "184": 0.4456521739130436, "185": 0.4432432432432434, "186": 0.4462365591397851, "187": 0.4438502673796793, "188": 0.4414893617021278, "189": 0.4391534391534393, "190": 0.43684210526315803, "191": 0.43455497382198965, "192": 0.4322916666666668, "193": 0.43005181347150273, "194": 0.4278350515463919, "195": 0.4256410256410258, "196": 0.4234693877551022, "197": 0.4213197969543149, "198": 0.42424242424242437, "199": 0.4271356783919599, "200": 0.42500000000000016, "201": 0.4228855721393036, "202": 0.42079207920792094, "203": 0.41871921182266025, "204": 0.4166666666666668, "205": 0.41463414634146356, "206": 0.4126213592233011, "207": 0.41062801932367166, "208": 0.4086538461538463, "209": 0.40669856459330156, "210": 0.4047619047619049, "211": 0.4028436018957347, "212": 0.4009433962264152, "213": 0.3990610328638499, "214": 0.39719626168224315, "215": 0.3953488372093025, "216": 0.39351851851851866, "217": 0.3917050691244241, "218": 0.38990825688073405, "219": 0.3926940639269408, "220": 0.39545454545454556, "221": 0.3936651583710409, "222": 0.3963963963963965, "223": 0.39461883408071763, "224": 0.39285714285714296, "225": 0.39111111111111124, "226": 0.38938053097345143, "227": 0.3876651982378856, "228": 0.3859649122807019, "229": 0.38427947598253287, "230": 0.38260869565217404, "231": 0.3852813852813854, "232": 0.38362068965517254, "233": 0.38197424892703874, "234": 0.3803418803418805, "235": 0.37872340425531925, "236": 0.3771186440677967, "237": 0.3755274261603377, "238": 0.3739495798319329, "239": 0.37656903765690386, "240": 0.3750000000000001, "241": 0.37344398340248974, "242": 0.3760330578512398, "243": 0.37448559670781906, "244": 0.3729508196721313, "245": 0.37142857142857155, "246": 0.369918699186992, "247": 0.36842105263157904, "248": 0.36693548387096786, "249": 0.36546184738955834, "250": 0.3680000000000001, "251": 0.3705179282868527, "252": 0.3690476190476192, "253": 0.3675889328063242, "254": 0.3661417322834647, "255": 0.36470588235294127, "256": 0.3632812500000001, "257": 0.36186770428015574, "258": 0.36046511627906985, "259": 0.3590733590733592, "260": 0.3576923076923078, "261": 0.36015325670498094, "262": 0.35877862595419857, "263": 0.35741444866920163, "264": 0.3560606060606062, "265": 0.35471698113207556, "266": 0.35338345864661663, "267": 0.35205992509363304, "268": 0.35074626865671654, "269": 0.34944237918215626, "270": 0.34814814814814826, "271": 0.3468634686346865, "272": 0.3455882352941178, "273": 0.3443223443223445, "274": 0.34306569343065707, "275": 0.34181818181818197, "276": 0.3405797101449277, "277": 0.34296028880866447, "278": 0.3417266187050362, "279": 0.34050179211469556, "280": 0.3428571428571431, "281": 0.34519572953736677, "282": 0.343971631205674, "283": 0.34275618374558325, "284": 0.3415492957746481, "285": 0.3403508771929827, "286": 0.3391608391608394, "287": 0.3379790940766553, "288": 0.33680555555555575, "289": 0.3356401384083047, "290": 0.3379310344827588, "291": 0.336769759450172, "292": 0.33904109589041115, "293": 0.3378839590443688, "294": 0.3367346938775512, "295": 0.33559322033898326, "296": 0.33445945945945965, "297": 0.33333333333333354, "298": 0.3322147651006713, "299": 0.33110367892976605, "300": 0.3300000000000002, "301": 0.32890365448505005, "302": 0.327814569536424, "303": 0.3300330033003302, "304": 0.32894736842105277, "305": 0.32786885245901654, "306": 0.32679738562091515, "307": 0.3257328990228014, "308": 0.3246753246753248, "309": 0.32362459546925576, "310": 0.3225806451612904, "311": 0.32154340836012874, "312": 0.32051282051282065, "313": 0.31948881789137396, "314": 0.318471337579618, "315": 0.3174603174603176, "316": 0.3196202531645571, "317": 0.3186119873817036, "318": 0.3176100628930819, "319": 0.3166144200626961, "320": 0.31562500000000016, "321": 0.3146417445482868, "322": 0.31366459627329213, "323": 0.3126934984520126, "324": 0.3117283950617286, "325": 0.31076923076923096, "326": 0.30981595092024555, "327": 0.30886850152905215, "328": 0.30792682926829285, "329": 0.31003039513677827, "330": 0.30909090909090925, "331": 0.30815709969788535, "332": 0.3102409638554219, "333": 0.3093093093093095, "334": 0.3083832335329343, "335": 0.30746268656716436, "336": 0.30654761904761924, "337": 0.30563798219584587, "338": 0.30473372781065106, "339": 0.3038348082595872, "340": 0.3029411764705884, "341": 0.3020527859237538, "342": 0.301169590643275, "343": 0.3002915451895045, "344": 0.302325581395349, "345": 0.3043478260869567, "346": 0.30346820809248576, "347": 0.3025936599423633, "348": 0.3017241379310347, "349": 0.30085959885386837, "350": 0.30000000000000016, "351": 0.2991452991452993, "352": 0.2982954545454547, "353": 0.2974504249291786, "354": 0.2966101694915256, "355": 0.2957746478873241, "356": 0.2977528089887642, "357": 0.29691876750700297, "358": 0.29608938547486047, "359": 0.29526462395543185, "360": 0.2944444444444445, "361": 0.293628808864266, "362": 0.29281767955801113, "363": 0.2920110192837466, "364": 0.2912087912087913, "365": 0.2904109589041097, "366": 0.2896174863387979, "367": 0.2888283378746595, "368": 0.2880434782608697, "369": 0.2872628726287264, "370": 0.2864864864864866, "371": 0.2857142857142858, "372": 0.28494623655913986, "373": 0.2841823056300269, "374": 0.2834224598930482, "375": 0.28266666666666673, "376": 0.28457446808510645, "377": 0.28381962864721494, "378": 0.28306878306878314, "379": 0.28232189973614785, "380": 0.28157894736842115, "381": 0.28346456692913397, "382": 0.28272251308900537, "383": 0.2819843342036555, "384": 0.28125000000000017, "385": 0.28051948051948067, "386": 0.2797927461139898, "387": 0.27906976744186063, "388": 0.27835051546391765, "389": 0.2776349614395888, "390": 0.27948717948717966, "391": 0.27877237851662423, "392": 0.2780612244897961, "393": 0.27735368956743023, "394": 0.2766497461928936, "395": 0.2759493670886078, "396": 0.2752525252525254, "397": 0.2745591939546601, "398": 0.2738693467336685, "399": 0.27318295739348386, "400": 0.27250000000000013}, "precise": {"elect": true, "vote": true, "presid": true, "pardon": true, "administr": true, "campaign": true, "inaugur": false, "win": false, "support": false, "elector": true, "result": true, "state": true, "presidenti": true, "ralli": false, "overturn": false, "voter": true, "vaccin": false, "victori": false, "conced": false, "fraud": true, "offic": true, "plan": true, "call": false, "recount": true, "offici": true, "team": false, "transit": true, "claim": true, "secretari": true, "former": false, "court": true, "lawsuit": true, "lost": false, "poll": true, "impeach": true, "trump": false, "nation": true, "count": true, "lead": false, "certifi": true, "lie": false, "legal": true, "bill": true, "polici": true, "democraci": true, "secur": false, "last": false, "feder": true, "year": false, "defens": false, "polit": true, "speech": false, "said": false, "law": true, "ballot": true, "veto": true, "overrid": false, "file": true, "colleg": false, "relief": false, "foreign": false, "cast": true, "widespread": false, "dose": false, "judg": true, "sign": true, "evid": true, "packag": false, "refus": false, "mail": true, "dismiss": false, "challeng": true, "reject": true, "receiv": false, "pass": false, "stimulu": false, "appeal": true, "president-elect": true, "alleg": false, "effort": false, "pick": false, "execut": true, "deliv": false, "check": true, "counti": true, "order": true, "first": false, "leav": false, "certif": true, "nomin": true, "attempt": false, "week": false, "advis": false, "popular": false, "govern": true, "coup": false, "bid": false, "block": false, "fund": true, "day": false, "remov": true, "lawyer": false, "race": false, "winner": false, "introduc": false, "demand": false, "econom": false, "retir": false, "agenc": true, "final": false, "threaten": false, "senior": true, "confirm": true, "next": false, "vice": false, "debat": false, "nomine": true, "increas": false, "cabinet": true, "object": false, "revers": true, "invok": false, "million": false, "health": false, "immigr": true, "announc": false, "democrat": true, "investig": false, "outcom": false, "chief": false, "rig": false, "process": true, "climat": false, "suit": false, "brief": true, "staff": false, "intellig": true, "counsel": true, "tax": true, "appoint": true, "member": true, "attorney": false, "new": false, "remark": false, "affirm": true, "gener": true, "son": false, "cut": false, "take": false, "acknowledg": false, "educ": false, "director": true, "woman": false, "project": false, "militari": false, "troop": false, "oath": true, "commun": true, "republican": true, "second": false, "earli": false, "articl": true, "time": false, "power": true, "clemenc": false, "term": true, "senat": true, "peac": false, "turnout": true, "pressur": false, "posit": true, "crimin": false, "press": false, "death": false, "cooper": false, "confer": false, "runoff": false, "incit": false, "crime": true, "american": false, "pay": false, "famili": false, "address": false, "fire": false, "alli": false, "violenc": true, "separ": false, "peopl": false, "riot": false, "rais": false, "hold": false, "mob": false, "border": false, "charg": false, "resign": false, "children": false, "pro-trump": false, "polic": true, "account": true, "money": false, "attack": false, "die": false, "protest": false, "tri": false, "say": false, "suspend": false, "rioter": false, "steal": false, "arrest": false, "twitter": false, "capitol": false, "stop": false, "assault": false, "get": false, "find": false, "ban": false, "congratul": false, "proof": false, "appointe": true, "justic": true, "domest": false, "governor": true, "enemi": false, "servic": false, "cheat": false, "terrorist": false, "destroy": false, "travel": false, "leader": false, "compani": false, "machin": true, "ask": false, "end": false, "mani": false, "spent": false, "chines": false, "mask": false, "media": false, "major": true, "believ": false, "russian": false, "need": true, "hour": false, "lose": false, "work": false, "wear": false, "disinform": false, "countri": false, "viru": false, "parti": true, "want": true, "group": false, "send": false, "think": false, "uniti": false, "know": false, "messag": false, "go": false, "make": false, "tweet": false, "corrupt": true, "name": false, "let": false, "white": false, "illeg": false, "'re": false, "thing": false, "way": false, "black": false, "person": false, "email": false, "man": false, "lock": false, "paid": false, "fight": false, "done": false, "right": true, "clear": false, "deni": false, "act": true, "base": true, "diplomat": false, "live": false, "golf": false, "see": false, "cours": false, "veteran": false, "save": false, "play": false, "choos": true, "'ve": false, "hear": true, "pledg": false, "today": false, "break": false, "dog": false, "seen": false, "stand": false, "news": false, "got": false, "step": false, "job": false, "record": true, "coverag": false, "credit": false, "doctor": false, "good": false, "report": false, "releas": false, "close": false, "crowd": false, "love": false, "pre": false, "led": false, "video": false, "statement": true, "post": false, "come": false, "flag": false, "depart": false, "watch": false, "letter": false, "histor": false, "flip": false, "tie": false, "blue": false, "full": false, "look": false, "defend": true, "talk": false, "bad": false, "open": true, "landslid": false, "agreement": false, "thread": false, "read": false, "faith": false, "kid": false, "secret": false, "favor": false, "remain": false, "truth": false, "disput": false, "privat": true, "answer": true, "stori": false, "run": false, "admit": false, "great": false, "stock": false, "stage": false, "document": false, "big": false, "minut": false, "matter": false, "market": true, "interview": false, "reveal": false, "better": false, "import": false, "loser": false, "financi": false, "uselect": false, "oper": false, "confid": false, "bet": false, "speak": false, "wrote": false, "fuck": false, "trust": false, "walk": false, "wife": false, "biggest": false, "hous": false, "hell": false, "mark": true, "arriv": false, "photo": false, "legaci": false, "biden": false, "moder": true, "true": false, "least": false, "embarrass": false, "traitor": false, "word": false, "entir": false, "shut": false, "thank": false, "cancel": true, "hurt": false, "pleas": false, "grift": false, "note": false, "happi": false, "crazi": false, "gone": false, "endors": false, "sound": false, "surpris": false}, "recalled": ["democratization", "position", "voter", "Record", "choose", "mark", "offices", "government", "party", "bill", "File", "power", "Counsel", "accountability", "Claim", "director", "nationalization", "Confirmation", "Certification", "oath", "governor", "police", "Impeachment", "wants", "challenger", "hearing", "nomination", "order", "community", "Pardon", "Crime", "needs", "voting", "ballot", "member", "violence", "Answer", "caste", "moderate", "immigration", "republicanism", "presidential", "campaign", "open", "Count", "electorate", "federalism", "democracy", "Evidence", "official", "Lawsuit", "legally", "check", "law", "intelligence", "Affirmed", "Defendant", "mail", "acting", "appointee", "nominee", "cancellation", "poll", "politics", "election", "Appeal", "Fraud", "Reverse", "remove", "machine", "sign", "statement", "Judge", "turnout", "county", "seniority", "cabinet", "policy", "senate", "term", "tax", "Plan", "privatization", "certify", "agency", "general", "article", "majority", "process", "Brief", "state", "executive", "transitivity", "secretary", "president-elect", "Court", "results", "corruption", "rights", "fund", "veto", "justice", "base", "reject", "president", "administration", "market", "recount", "appointment"]}}